LICENSE
echo1_coco_builder/__init__.py
echo1_coco_builder/annotations_builder.py
echo1_coco_builder/coco/CocoAnnotation.py
echo1_coco_builder/coco/CocoCategory.py
echo1_coco_builder/coco/CocoImage.py
echo1_coco_builder/coco/CocoInfo.py
echo1_coco_builder/coco/CocoResult.py
echo1_coco_builder/results_builder.py
echo1_coco_builder-0.1.8.dist-info/LICENSE
echo1_coco_builder-0.1.8.dist-info/WHEEL
echo1_coco_builder-0.1.8.dist-info/METADATA
echo1_coco_builder-0.1.8.dist-info/RECORD
