Metadata-Version: 2.1
Name: echo1-coco-builder
Version: 0.1.8
Summary: 
Home-page: https://github.com/e1-io/echo1-coco-builder
License: MIT
Author: Michael Mohamed
Author-email: michael.mohamed@echo1.io
Requires-Python: >=3.7.1,<4.0
Classifier: License :: OSI Approved :: MIT License
Classifier: Programming Language :: Python :: 3
Classifier: Programming Language :: Python :: 3.10
Classifier: Programming Language :: Python :: 3.8
Classifier: Programming Language :: Python :: 3.9
Requires-Dist: loguru (>=0.5.3,<0.6.0)
Requires-Dist: marshmallow (>=3.14.1,<4.0.0)
Requires-Dist: pandas (>=1.3.5,<2.0.0)
Project-URL: Repository, https://github.com/e1-io/echo1-coco-builder
